dsqlenv/__init__.py
dsqlenv/cli.py
dsqlenv/config.py
dsqlenv/core.py
dsqlenv/data.py
dsqlenv/encryption.py
dsqlenv/version.py
dsqlenv-1.0.3.dist-info/LICENSE
dsqlenv-1.0.3.dist-info/METADATA
dsqlenv-1.0.3.dist-info/WHEEL
dsqlenv-1.0.3.dist-info/entry_points.txt
dsqlenv-1.0.3.dist-info/top_level.txt
dsqlenv-1.0.3.dist-info/RECORD
