Metadata-Version: 2.1
Name: dsqlenv
Version: 1.0.3
Summary: A tool for database operations with encryption and decryption, configurable table and column names, and additional CLI features.
Home-page: https://gitee.com/iint/dsql
Author: Zhao Sheng
Author-email: zhaosheng@nuaa.edu.cn
Classifier: Programming Language :: Python :: 3
Classifier: License :: OSI Approved :: MIT License
Classifier: Operating System :: OS Independent
Requires-Python: >=3.10
License-File: LICENSE
